parallel_connection/__init__.py
parallel_connection/parallel_connection.py
parallel_connection-0.1.2.dist-info/DESCRIPTION.rst
parallel_connection-0.1.2.dist-info/METADATA
parallel_connection-0.1.2.dist-info/RECORD
parallel_connection-0.1.2.dist-info/WHEEL
parallel_connection-0.1.2.dist-info/metadata.json
parallel_connection-0.1.2.dist-info/top_level.txt
