Metadata-Version: 2.0
Name: parallel-connection
Version: 0.1.2
Summary: A package to query Postgres databases in parallel
Home-page: https://github.com/godatadriven/ParallelConnection
Author: Niels Zeilemaker, Giovanni Lanzani
Author-email: niels@zeilemaker.nl, giovanni@lanzani.nl
License: Apache 2.0
Keywords: development databases parallel
Platform: UNKNOWN
Classifier: Development Status :: 4 - Beta
Classifier: Intended Audience :: Developers
Classifier: Topic :: Database :: Front-Ends
Classifier: License :: OSI Approved :: Apache Software License
Classifier: Programming Language :: Python :: 2
Classifier: Programming Language :: Python :: 2.6
Classifier: Programming Language :: Python :: 2.7
Classifier: Programming Language :: Python :: 3
Classifier: Programming Language :: Python :: 3.2
Classifier: Programming Language :: Python :: 3.3
Classifier: Programming Language :: Python :: 3.4
Classifier: Programming Language :: Python :: 3.5
Provides-Extra: test
Requires-Dist: nose; extra == 'test'
